LICENSE
MANIFEST.in
README.rst
requirements.txt
setup.py
./bin/pyhrf_crop_data
./bin/pyhrf_extract_cc_vol
./bin/pyhrf_glm_buildcfg
./bin/pyhrf_glm_estim
./bin/pyhrf_gls
./bin/pyhrf_info
./bin/pyhrf_jde_buildcfg
./bin/pyhrf_jde_estim
./bin/pyhrf_jde_vem_analysis
./bin/pyhrf_list_datafiles
./bin/pyhrf_maketests
./bin/pyhrf_mask_from_bold
./bin/pyhrf_nii_mean
./bin/pyhrf_nii_split
./bin/pyhrf_nii_std
./bin/pyhrf_parcellate_glm
./bin/pyhrf_parcellate_spatial
./bin/pyhrf_parcellation_extract
./bin/pyhrf_parcellation_merge_small
./bin/pyhrf_plot_mip
./bin/pyhrf_plot_slice
./bin/pyhrf_project_data
./bin/pyhrf_rfir_buildcfg
./bin/pyhrf_rfir_estim
./bin/pyhrf_script_shortcut
./bin/pyhrf_spm_cpt_con_var
./bin/pyhrf_spm_fixnames
./bin/pyhrf_spm_gen_design_signal
./bin/pyhrf_src_path
./bin/pyhrf_validate
python/pyhrf/__init__.py
python/pyhrf/_verbose.py
python/pyhrf/configuration.py
python/pyhrf/core.py
python/pyhrf/glm.py
python/pyhrf/graph.py
python/pyhrf/grid.py
python/pyhrf/ndarray.py
python/pyhrf/paradigm.py
python/pyhrf/parallel.py
python/pyhrf/parcellation.py
python/pyhrf/plot.py
python/pyhrf/rfir.py
python/pyhrf/surface.py
python/pyhrf/usemode.py
python/pyhrf/version.py
python/pyhrf/xmlio.py
python/pyhrf.egg-info/PKG-INFO
python/pyhrf.egg-info/SOURCES.txt
python/pyhrf.egg-info/dependency_links.txt
python/pyhrf.egg-info/not-zip-safe
python/pyhrf.egg-info/requires.txt
python/pyhrf.egg-info/top_level.txt
python/pyhrf/boldsynth/__init__.py
python/pyhrf/boldsynth/field.py
python/pyhrf/boldsynth/hrf.py
python/pyhrf/boldsynth/scenarios.py
python/pyhrf/boldsynth/spatialconfig.py
python/pyhrf/boldsynth/pottsfield/__init__.py
python/pyhrf/boldsynth/pottsfield/swendsenwang.py
python/pyhrf/datafiles/SPM_v12.mat.gz
python/pyhrf/datafiles/SPM_v5.mat.gz
python/pyhrf/datafiles/SPM_v8.mat.gz
python/pyhrf/datafiles/cortex_occipital_hrf_territories_3mm.nii
python/pyhrf/datafiles/cortex_occipital_hrf_territories_convex_hull.tgz
python/pyhrf/datafiles/cortex_occipital_right_GWmask_3mm.nii.gz
python/pyhrf/datafiles/cortex_occipital_white_surf.gii.gz
python/pyhrf/datafiles/dummySmallBOLD.nii.gz
python/pyhrf/datafiles/dummySmallMask.nii.gz
python/pyhrf/datafiles/paradigm_V4.csv
