Metadata-Version: 1.1
Name: pyhrf
Version: 0.5.0.post1
Summary: Analysis of fMRI data based on the study of hemodynamics
Home-page: http://pyhrf.org
Author: Jaime Arias
Author-email: jaime.arias@inria.fr
License: CeCILLv2
Download-URL: https://github.com/pyhrf/pyhrf
Platform: UNKNOWN
Classifier: Development Status :: 3 - Alpha
Classifier: Environment :: Console
Classifier: Intended Audience :: Science/Research
Classifier: License :: OSI Approved
Classifier: Programming Language :: Python :: 2
Classifier: Programming Language :: Python :: 2.7
Classifier: Programming Language :: C
Classifier: Programming Language :: Python :: Implementation :: CPython
Classifier: Topic :: Scientific/Engineering
Classifier: Topic :: Scientific/Engineering :: Mathematics
Classifier: Topic :: Scientific/Engineering :: Medical Science Apps.
